passwordmaker_pkg/PasswordMaker.py
passwordmaker_pkg/PasswordTools.py
passwordmaker_pkg/__init__.py
passwordmaker_pkg/maker.py
passwordmaker_pkg_leonardomartelli-1.2.0.dist-info/LICENSE
passwordmaker_pkg_leonardomartelli-1.2.0.dist-info/METADATA
passwordmaker_pkg_leonardomartelli-1.2.0.dist-info/WHEEL
passwordmaker_pkg_leonardomartelli-1.2.0.dist-info/top_level.txt
passwordmaker_pkg_leonardomartelli-1.2.0.dist-info/RECORD
